archive/cmd/pkl-gen-go/pkl-gen-python.py
archive/cmd/pkl-gen-python/pkl-gen-python.py
old/pkl-gen-python/generate.py
old/pkl-gen-python/main.py
out/ExtendModule_pkl.py
out/ExtendingOpenClass_pkl.py
out/Foo_pkl.py
out/Imports_pkl.py
out/MyModule_pkl.py
out/com_example_ExtendedSimple_pkl.py
out/com_example_Simple_pkl.py
out/lib3_pkl.py
out/union_pkl.py
pkll/VERSION
pkll/__init__.py
pkll/evaluator.py
pkll/handler.py
pkll/parser.py
pkll/server.py
pkll/msgapi/__init__.py
pkll/msgapi/code.py
pkll/msgapi/incoming.py
pkll/msgapi/outgoing.py
scripts/download_binary.py
scripts/eval.py
tests/test_evaluator.py
tests/test_parser.py
tests/test_responses.py
tests/test_server.py
pkll-0.1.10.dist-info/LICENSE
pkll-0.1.10.dist-info/METADATA
pkll-0.1.10.dist-info/WHEEL
pkll-0.1.10.dist-info/top_level.txt
pkll-0.1.10.dist-info/RECORD
