Metadata-Version: 2.1
Name: pkll
Version: 0.1.10
Summary: Python library for Apple's PKL.
Author-email: Jungwoo Yang <jwyang0213@gmail.com>
License: MIT License
Project-URL: Homepage, https://github.com/jw-y/pkll
Project-URL: Bug Reports, https://github.com/jw-y/pkll/issues
Project-URL: Source, https://github.com/jw-y/pkll
Classifier: Programming Language :: Python :: 3
Classifier: License :: OSI Approved :: MIT License
Classifier: Operating System :: OS Independent
Requires-Python: >=3.6
License-File: LICENSE
Requires-Dist: msgpack >=1.0.8
Provides-Extra: dev
Requires-Dist: pre-commit ; extra == 'dev'
Requires-Dist: black ; extra == 'dev'
Requires-Dist: isort ; extra == 'dev'
Requires-Dist: mypy ; extra == 'dev'
Requires-Dist: pylint ; extra == 'dev'
Requires-Dist: pytest ; extra == 'dev'
Requires-Dist: pytest-cov ; extra == 'dev'
Requires-Dist: tox ; extra == 'dev'
